netpack/__init__.py
netpack/func.py
netpack/test.py
netpackAIO-0.0.8.dist-info/LICENSE
netpackAIO-0.0.8.dist-info/METADATA
netpackAIO-0.0.8.dist-info/WHEEL
netpackAIO-0.0.8.dist-info/top_level.txt
netpackAIO-0.0.8.dist-info/RECORD
