Metadata-Version: 2.1
Name: netpackAIO
Version: 0.0.8
Summary: A Python package for performing network-related tasks
Home-page: https://github.com/crusaderay/netpack
Author: Dongjie Zhang
Author-email: crusade.ray@gmail.com
License: UNKNOWN
Platform: UNKNOWN
Classifier: Programming Language :: Python :: 3
Classifier: License :: OSI Approved :: MIT License
Classifier: Operating System :: OS Independent
Requires-Python: >=3.6
License-File: LICENSE
Requires-Dist: bs4 (==0.0.1)
Requires-Dist: requests (==2.28.2)
